calories_properties_pkg/__init__.py
calories_properties_pkg/calories_properties.py
calories_properties_pkg-0.0.1.dist-info/LICENSE
calories_properties_pkg-0.0.1.dist-info/METADATA
calories_properties_pkg-0.0.1.dist-info/WHEEL
calories_properties_pkg-0.0.1.dist-info/top_level.txt
calories_properties_pkg-0.0.1.dist-info/RECORD
